Workbook

Sheet Dashboard
A1: Policy Holding Sale Event Tape v0.4
A2: Built / revised | B2: 46210
A3: Total rows | B3: =COUNTA(Event_Tape!A2:A400) -> 12
A4: Tier1 confirmed | B4: =COUNTIF(Event_Tape!J2:J400,"Tier1_confirmed") -> 9
A5: Tier2 candidates | B5: =COUNTIF(Event_Tape!J2:J400,"Tier2_candidate") -> 3
A6: ABM candidates | B6: =COUNTIF(Event_Tape!BM2:BM400,"Yes") -> 7
A7: Rows needing price/liquidity data | B7: CAR/ADV/free_float/market cap columns remain blank by design
A8: Status: candidate | B8: =COUNTIF(Event_Tape!C2:C400,"candidate") -> 3
A9: Route | B9: Count
A10: secondary_offering | B10: =COUNTIF(Event_Tape!L2:L400,A10) -> 9
A11: toSTNeT_3 | B11: =COUNTIF(Event_Tape!L2:L400,A11) -> 2
A12: share_forward | B12: =COUNTIF(Event_Tape!L2:L400,A12) -> 1
A13: block_trade | B13: =COUNTIF(Event_Tape!L2:L400,A13) -> 0
A14: open_market_sale | B14: =COUNTIF(Event_Tape!L2:L400,A14) -> 0
A15: market_sale_undetermined | B15: =COUNTIF(Event_Tape!L2:L400,A15) -> 0
A16: mixed | B16: =COUNTIF(Event_Tape!L2:L400,"mixed") -> 0
A17: unknown | B17: =COUNTIF(Event_Tape!L2:L400,"unknown") -> 0
A18: blank | B18: =COUNTIFS(Event_Tape!A2:A400,"<>",Event_Tape!L2:L400,"") -> 0
A20: Next actions
A21: 1 | B21: 一次PDFの取得・保存。Source_LogのAisin URL異常とYahoo CDN直リンクを優先確認
A22: 2 | B22: disclosure_time/after_closeをTDnetで確認し、day0規則でCARの基準日を確定
A23: 3 | B23: 価格系列を取得して announcement/pricing/settlement CAR、drift、recoveryを埋める
A24: 4 | B24: ADV20/ADV60/free_float/market cap を取得して size variables を計算
A25: 5 | B25: Tier1 A/Bで size/ADV → square-root → route/support FE → route choice を検証
A26: 6 | B26: 残差が構造タグに集中する場合のみABM_candidate_flagを維持

Sheet Event_Tape
A1: event_group_id | B1: event_leg_id | C1: status | D1: issuer_code | E1: issuer_name | F1: issuer_market | G1: seller_name | H1: seller_type | I1: relationship | J1: event_tier | K1: event_role | L1: sale_route | M1: absorption_route | N1: support_buyback | O1: support_OA | P1: support_lockup | Q1: support_stabilization | R1: disclosure_time | S1: after_close | T1: announce_datetime | U1: pricing_date | V1: settlement_date | W1: trade_date | X1: quantity_basis | Y1: value_basis | Z1: initial_offer_shares | AA1: final_offer_shares | AB1: OA_shares_max | AC1: OA_exercised_shares | AD1: sold_shares | AE1: sold_value_JPY | AF1: pre_holding_shares | AG1: post_holding_shares | AH1: ADV20_shares | AI1: ADV60_shares | AJ1: free_float_shares | AK1: market_cap_JPY | AL1: size_ADV20_calc | AM1: size_ADV60_calc | AN1: size_free_float_calc | AO1: size_market_cap_calc | AP1: offer_price_JPY | AQ1: previous_close_JPY | AR1: discount_calc | AS1: buyback_size_shares | AT1: buyback_value_JPY | AU1: buyback_method | AV1: buyback_window | AW1: buyback_cancellation | AX1: lockup_days | AY1: lead_underwriter | AZ1: seller_breakdown | BA1: activist_pressure | BB1: announcement_CAR_m1_p1 | BC1: announcement_CAR_0_p1 | BD1: pricing_CAR_m1_p1 | BE1: settlement_CAR_m1_p1 | BF1: drift_ann_to_pricing | BG1: recovery_5d | BH1: recovery_20d | BI1: recovery_60d | BJ1: abnormal_volume_0_p3 | BK1: route_notes | BL1: mechanism_hypothesis | BM1: ABM_candidate_flag | BN1: confidence_policy_holding | BO1: source_primary_url | BP1: source_secondary_url | BQ1: notes
A2: G001 | B2: L001 | C2: seeded | D2: 6902 | E2: DENSO | F2: TSE Prime | G2: Toyota Industries; Toyota Motor; Aisin (per secondary distribution disclosures) | H2: parent_or_affiliate | I2: Toyota Group cross-shareholding | J2: Tier1_confirmed | K2: announcement | L2: secondary_offering | M2: public_offering | N2: TRUE | T2: 45259 | AL2: =IF(AND(AD2<>"",AH2<>""),AD2/AH2,"") | AM2: =IF(AND(AD2<>"",AI2<>""),AD2/AI2,"") | AN2: =IF(AND(AD2<>"",AJ2<>""),AD2/AJ2,"") | AO2: =IF(AND(AE2<>"",AK2<>""),AE2/AK2,"") | AR2: =IF(AND(AP2<>"",AQ2<>""),AP2/AQ2-1,"") | BK2: DENSO secondary distribution; Toyota Industries explicitly announced participation as seller. | BL2: Cross-shareholding unwind via underwritten secondary; useful as 2023 precedent. | BM2: No | BN2: B_strong_inference | BO2: https://www.toyota-industries.com/news/2023/11/29/008606/index.html | BQ2: Need DENSO primary PDF for full seller breakdown and pricing dates.
A3: G002 | B3: L001 | C3: seeded | D3: 6201 | E3: Toyota Industries | F3: TSE Prime / NSE Premier | G3: DENSO Corporation | H3: parent_or_affiliate | I3: Toyota Group cross-shareholding | J3: Tier1_confirmed | K3: announcement | L3: share_forward | M3: counterparty_bank_forward | N3: FALSE | O3: FALSE | P3: FALSE | Q3: FALSE | T3: 45380 | W3: 45380 | X3: announced_total | AD3: 29647895 | AF3: 29647895 | AG3: 0 | AL3: =IF(AND(AD3<>"",AH3<>""),AD3/AH3,"") | AM3: =IF(AND(AD3<>"",AI3<>""),AD3/AI3,"") | AN3: =IF(AND(AD3<>"",AJ3<>""),AD3/AJ3,"") | AO3: =IF(AND(AE3<>"",AK3<>""),AE3/AK3,"") | AR3: =IF(AND(AP3<>"",AQ3<>""),AP3/AQ3-1,"") | AU3: spot sale + share forward agreement | AV3: Mar/Jun/Sep/Dec 26 settlements, Jun 2024-Jun 2026 | BK3: 2,965,595 shares spot sale; 26,682,300 shares forward in 9 quarterly settlements. | BL3: Designed explicitly to limit market impact of simultaneous large share release. | BM3: Yes | BN3: A_explicit_policy_holding | BO3: https://www.nse.or.jp/listing/search/files/140120240328562091.pdf | BQ3: Not a standard secondary offering; useful for route-choice/tail-impact comparison.
A4: G003 | B4: L001 | C4: seeded | D4: 7259 | E4: Aisin | F4: TSE Prime / NSE Premier | G4: DENSO; Toyota Industries; Toyota Motor | H4: parent_or_affiliate | I4: Toyota Group cross-shareholding | J4: Tier1_confirmed | K4: announcement | L4: secondary_offering | M4: public_offering | N4: TRUE | O4: TRUE | T4: 45470 | X4: announced_total | AB4: 5079300 | AD4: 33862500 | AL4: =IF(AND(AD4<>"",AH4<>""),AD4/AH4,"") | AM4: =IF(AND(AD4<>"",AI4<>""),AD4/AI4,"") | AN4: =IF(AND(AD4<>"",AJ4<>""),AD4/AJ4,"") | AO4: =IF(AND(AE4<>"",AK4<>""),AE4/AK4,"") | AR4: =IF(AND(AP4<>"",AQ4<>""),AP4/AQ4-1,"") | AS4: 17000000 | AT4: 100000000000 | AU4: market repurchase program | AV4: announced same day, max ¥100bn / 17m shares | BK4: Secondary offering by underwriters; OA max 5,079,300 shares. Company also announced buyback/cancellation. | BL4: Classic secondary + buyback support; compare announcement/pricing/recovery. | BM4: Yes | BN4: A_explicit_policy_holding | BO4: https://www.aisin.com/en/news/uploads/2027062701en.pdf | BP4: https://www.reuters.com/business/autos-transportation/toyota-group-companies-offload-some-1-bln-aisin-shares-2024-06-27/ | BQ4: Aisin PDF URL path contains 2027062701en.pdf but document date is 2024-06-27. / Source_Log上もAisin一次PDF URLのパス異常(2027を含む)を記録。一次PDF保存必須。
A5: G004 | B5: L001 | C5: seeded | D5: 7267 | E5: Honda Motor | F5: TSE Prime | G5: Tokio Marine & Nichido; Sompo Japan; MS&AD units; MUFG Trust; Mizuho Trust; MUFG Bank; Saitama Resona; Mizuho Bank; Nomura Trust | H5: mixed_financials | I5: insurance/bank policy holdings | J5: Tier1_confirmed | K5: announcement | L5: secondary_offering | M5: public_offering | N5: TRUE | O5: TRUE | Q5: TRUE | T5: 45477 | X5: announced_total | Y5: estimate_close_price | AB5: 38981900 | AD5: 259879700 | AE5: 535000000000 | AL5: =IF(AND(AD5<>"",AH5<>""),AD5/AH5,"") | AM5: =IF(AND(AD5<>"",AI5<>""),AD5/AI5,"") | AN5: =IF(AND(AD5<>"",AJ5<>""),AD5/AJ5,"") | AO5: =IF(AND(AE5<>"",AK5<>""),AE5/AK5,"") | AR5: =IF(AND(AP5<>"",AQ5<>""),AP5/AQ5-1,"") | AS5: 180000000 | AT5: 300000000000 | AU5: market buyback / ToSTNeT-3 possible, paused during offering window | AV5: 2024-05-13 to 2025-03-31 | BK5: Large insurer/bank unwinding; existing ¥300bn buyback authorization but buyback suspended from 2024-07-05 to delivery date. | BL5: Tests support-vs-paused buyback, financial-seller overhang, and syndicate stabilization. | BM5: Yes | BN5: A_explicit_policy_holding | BO5: https://global.honda/content/dam/site/global-jp/news-new/cq_img/2024/07/c240704/c240704.pdf | BP5: https://www.reuters.com/business/autos-transportation/japanese-insurers-banks-sell-honda-shares-worth-33-bln-filing-shows-2024-07-04/ | BQ5: Reuters value estimate based on shares and close price; confirm final offer price separately. / sold_value_JPYはReuters推定値のためvalue_basis=estimate_close_price。最終条件・一次PDFで要更新。
A6: G005 | B6: L001 | C6: seeded | D6: 8154 | E6: Kaga Electronics | F6: TSE Prime | G6: MUFG Bank; Mizuho Bank; Sumitomo Mitsui Banking; Hokuriku Bank | H6: bank | I6: policy shareholders | J6: Tier1_confirmed | K6: buyback_decision | L6: toSTNeT_3 | M6: toSTNeT_3_buyback | N6: TRUE | O6: FALSE | Q6: FALSE | T6: 45876 | W6: 45877 | X6: resolution_max | Y6: resolution_max | AD6: 4920000 | AE6: 15000000000 | AL6: =IF(AND(AD6<>"",AH6<>""),AD6/AH6,"") | AM6: =IF(AND(AD6<>"",AI6<>""),AD6/AI6,"") | AN6: =IF(AND(AD6<>"",AJ6<>""),AD6/AJ6,"") | AO6: =IF(AND(AE6<>"",AK6<>""),AE6/AK6,"") | AQ6: 2938 | AR6: =IF(AND(AP6<>"",AQ6<>""),AP6/AQ6-1,"") | AS6: 4920000 | AT6: 15000000000 | AU6: ToSTNeT-3 | AV6: 2025-08-08 08:45 | BK6: Issuer says banks intend to sell under CG Code policy-holding reduction; company chose ToSTNeT-3 to reduce market impact. | BL6: Pure buyback absorption event; strong case for route vs market-disposal counterfactual. | BM6: Yes | BN6: A_explicit_policy_holding | BO6: https://www.taxan.co.jp/jp/ir/upload_file/tdnrelease/8154_20250807533725_P01_.pdf | BQ6: Includes explicit previous close (¥2,938) and max buyback amount. / sold_value_JPYは決議上の上限。4,920,000株×前日終値2,938円=約144.5億円だが、開示上限は150億円。実績は取得結果開示のbuyback_result legとして別途追加予定。
A7: G006 | B7: L001 | C7: seeded | D7: 3950 | E7: The Pack | F7: TSE Prime | G7: MUFG Bank; Marubeni; MUFG Trust; Daiwa House Industry; Sumitomo Life; Sompo Japan; Sumitomo Mitsui Trust; Marubeni Forest Links | H7: mixed | I7: major shareholders / likely policy holders | J7: Tier1_confirmed | K7: announcement | L7: secondary_offering | M7: public_offering | N7: TRUE | O7: TRUE | P7: TRUE | Q7: TRUE | T7: 45898 | X7: announced_total | AD7: 3720400 | AL7: =IF(AND(AD7<>"",AH7<>""),AD7/AH7,"") | AM7: =IF(AND(AD7<>"",AI7<>""),AD7/AI7,"") | AN7: =IF(AND(AD7<>"",AJ7<>""),AD7/AJ7,"") | AO7: =IF(AND(AE7<>"",AK7<>""),AE7/AK7,"") | AR7: =IF(AND(AP7<>"",AQ7<>""),AP7/AQ7-1,"") | AS7: 900000 | AT7: 1000000000 | AU7: market buyback including ToSTNeT-3 possible | AV7: 2025-02-13 to 2025-12-31; paused during offering delivery window | BK7: Secondary offering with multiple sellers, lockups, OA/greenshoe mechanics, and existing buyback authorization. | BL7: Good B-confidence event for support package and lockup tagging; confirm policy-holding language in seller filings. | BM7: Maybe | BN7: B_strong_inference | BO7: https://www.thepack.co.jp/dcms_media/other/2025.08.29b.pdf | BQ7: Need classify whether each seller is policy-holding unwind; first pass B not A.
A8: G007 | B8: L001 | C8: seeded | D8: 4246 | E8: Daikyo Nishikawa | F8: TSE Prime | G8: Nishikawa Rubber Industries | H8: business_company | I8: business partner / major shareholder | J8: Tier1_confirmed | K8: announcement | L8: secondary_offering | M8: public_offering | N8: TRUE | T8: 46041 | V8: 46048 | X8: announced_total | AD8: 3550000 | AE8: 2801944000 | AF8: 9450000 | AG8: 5900000 | AL8: =IF(AND(AD8<>"",AH8<>""),AD8/AH8,"") | AM8: =IF(AND(AD8<>"",AI8<>""),AD8/AI8,"") | AN8: =IF(AND(AD8<>"",AJ8<>""),AD8/AJ8,"") | AO8: =IF(AND(AE8<>"",AK8<>""),AE8/AK8,"") | AP8: 789.28 | AR8: =IF(AND(AP8<>"",AQ8<>""),AP8/AQ8-1,"") | AU8: ToSTNeT-3 buyback also used by issuer on 2026-01-09 | AV8: prior ToSTNeT-3 + offering | BK8: Seller cites plan to sell ¥10bn of policy holdings by FY2028; sale plus prior issuer ToSTNeT-3 changed ownership ratio. | BL8: Nice mixed absorption/offering event; compare ToSTNeT-3 leg and offering leg if detailed issuer docs found. | BM8: Yes | BN8: A_explicit_policy_holding | BO8: https://www.nishikawa-rbr.co.jp/upfile/20260119_3_news.pdf | BQ8: Need Daikyo Nishikawa primary offering/pricing PDFs for full issuer-side terms. / 売出金額2,801,944,000円の根拠(想定価格ベースか条件決定後か)を一次PDFで確認
A9: G008 | B9: L001 | C9: seeded | D9: 7974 | E9: Nintendo | F9: TSE Prime | G9: Nomura Trust Bank (MUFG Bank retirement benefit trust); Bank of Kyoto; DeNA; Resona Bank | H9: mixed_financials | I9: strategic/policy shareholders | J9: Tier1_confirmed | K9: announcement | L9: secondary_offering | M9: public_offering | N9: TRUE | O9: TRUE | Q9: TRUE | R9: 15:40 | S9: TRUE | T9: 46080 | X9: announced_total | Y9: estimate_close_price | Z9: 32697900 | AB9: 4904600 | AD9: 32697900 | AE9: 290000000000 | AL9: =IF(AND(AD9<>"",AH9<>""),AD9/AH9,"") | AM9: =IF(AND(AD9<>"",AI9<>""),AD9/AI9,"") | AN9: =IF(AND(AD9<>"",AJ9<>""),AD9/AJ9,"") | AO9: =IF(AND(AE9<>"",AK9<>""),AE9/AK9,"") | AR9: =IF(AND(AP9<>"",AQ9<>""),AP9/AQ9-1,"") | AS9: 14000000 | AT9: 100000000000 | AU9: ToSTNeT-3 | AV9: 2026-03-03 to 2026-03-04 | AW9: TRUE | AZ9: 野村信託銀行(退職給付信託三菱UFJ銀行口):16,149,900;京都銀行:10,000,000;DeNA:6,000,000;りそな銀行:548,000 | BA9: TRUE | BK9: Nintendo offering paired with ToSTNeT-3 buyback authorization; DeNA separately disclosed 6m planned sale. / 条件決定期間は2026-03-09〜2026-03-12。自己株取得に伴い買取引受・OAの売出株式数が減少し得る。 | BL9: High-quality route/support event: offering amount can shrink if sellers tender into ToSTNeT-3 buyback. | BM9: Yes | BN9: A_explicit_policy_holding | BO9: https://www.nintendo.co.jp/ir/pdf/2026/260227.pdf | BP9: https://www.nintendo.co.jp/ir/pdf/2026/260227_2.pdf | BQ9: Reuters estimates total value about ¥290bn excluding OA; final DeNA buyback tender changed remaining offering shares. / 開示は2026-02-27 15:40、引け後開示のためday 0=2026-03-02。DeNA売却の背景として旧村上系アクティビストの関与が報じられているためactivist_pressure=TRUE。 / OA上限株数4,904,600は一次PDFで要確認
A10: G008 | B10: L002 | C10: seeded | D10: 7974 | E10: Nintendo | F10: TSE Prime | G10: DeNA | H10: business_company | I10: strategic/policy shareholder | J10: Tier1_confirmed | K10: buyback_result | L10: toSTNeT_3 | M10: toSTNeT_3_buyback | N10: TRUE | O10: FALSE | Q10: FALSE | T10: 46084 | W10: 46084 | X10: executed_actual | Y10: executed_actual | AD10: 1657400 | AE10: 14500000000 | AF10: 8797000 | AG10: 7139600 | AL10: =IF(AND(AD10<>"",AH10<>""),AD10/AH10,"") | AM10: =IF(AND(AD10<>"",AI10<>""),AD10/AI10,"") | AN10: =IF(AND(AD10<>"",AJ10<>""),AD10/AJ10,"") | AO10: =IF(AND(AE10<>"",AK10<>""),AE10/AK10,"") | AR10: =IF(AND(AP10<>"",AQ10<>""),AP10/AQ10-1,"") | AS10: 11430000 | AT10: 99921060000 | AU10: ToSTNeT-3 result | AV10: 2026-03-03 | BK10: DeNA tendered 1,657,400 Nintendo shares into buyback; planned offering shares fell from 6,000,000 to 4,342,600. | BL10: Within-group leg showing absorption before offering; useful for parent-child event_group structure. | BM10: Yes | BN10: A_explicit_policy_holding | BO10: https://finance-frontend-pc-dist.west.edge.storage-yahoo.jp/disclosure/20260303/20260302574028.pdf | BP10: https://finance-frontend-pc-dist.west.edge.storage-yahoo.jp/disclosure/20260227/20260227571366.pdf | BQ10: Keep as separate leg under Nintendo group, not independent event. / Yahoo CDN直リンクは恒久URLとは限らないため一次PDF保存必須。 / 取得実績11,430,000株・総額99,921,060,000円は2026年3月期有報の自己株式消却記載(発行済株式11,430,000株減)と整合(S011)
A11: G009 | B11: L001 | C11: candidate | D11: 4063 | E11: 信越化学 | F11: TSE Prime | H11: financial_institutions | J11: Tier2_candidate | K11: announcement | L11: secondary_offering | AL11: =IF(AND(AD11<>"",AH11<>""),AD11/AH11,"") | AM11: =IF(AND(AD11<>"",AI11<>""),AD11/AI11,"") | AN11: =IF(AND(AD11<>"",AJ11<>""),AD11/AJ11,"") | AO11: =IF(AND(AE11<>"",AK11<>""),AE11/AK11,"") | AR11: =IF(AND(AP11<>"",AQ11<>""),AP11/AQ11-1,"") | BQ11: 要一次資料 / 報道: 金融8社による売出し、OA込み約1,300億円規模(2026年2月)。数値は一次PDF取得後に入力
A12: G010 | B12: L001 | C12: candidate | D12: 4062 | E12: イビデン | F12: TSE Prime | J12: Tier2_candidate | K12: announcement | L12: secondary_offering | AL12: =IF(AND(AD12<>"",AH12<>""),AD12/AH12,"") | AM12: =IF(AND(AD12<>"",AI12<>""),AD12/AI12,"") | AN12: =IF(AND(AD12<>"",AJ12<>""),AD12/AJ12,"") | AO12: =IF(AND(AE12<>"",AK12<>""),AE12/AK12,"") | AR12: =IF(AND(AP12<>"",AQ12<>""),AP12/AQ12-1,"") | BQ12: 要一次資料 / 報道: 2026年、数百億円規模の売出し。数値は一次PDF取得後に入力
A13: G011 | B13: L001 | C13: candidate | D13: 2871 | E13: ニチレイ | F13: TSE Prime | J13: Tier2_candidate | K13: announcement | L13: secondary_offering | AL13: =IF(AND(AD13<>"",AH13<>""),AD13/AH13,"") | AM13: =IF(AND(AD13<>"",AI13<>""),AD13/AI13,"") | AN13: =IF(AND(AD13<>"",AJ13<>""),AD13/AJ13,"") | AO13: =IF(AND(AE13<>"",AK13<>""),AE13/AK13,"") | AR13: =IF(AND(AP13<>"",AQ13<>""),AP13/AQ13-1,"") | BQ13: 要一次資料 / 報道: 2026年、数百億円規模の売出し。数値は一次PDF取得後に入力

Sheet Field_Dictionary
A1: field | B1: type | C1: description | D1: entry_notes
A2: event_group_id | B2: text | C2: 一連の政策保有株削減・売却意思決定を束ねる親ID | D2: 同一案件の売出し・自己株買い・条件決定・結果開示は同じgroup_id
A3: event_leg_id | B3: text | C3: 実際の売却/吸収/価格決定/結果開示の単位 | D3: 1行=issuer×route×tranche/leg。legは売主別に分割しない
A4: status | B4: enum | C4: 入力状態 | D4: seeded/candidate/needs_source_check/needs_price_data/complete/exclude
A5: issuer_code | B5: text | C5: 発行体の証券コード | D5: 不明・未検証は空欄
A6: issuer_name | B6: text | C6: 発行体名 | D6: 一次資料未取得の候補行は社名のみ可
A7: issuer_market | B7: text | C7: 市場区分 | D7: 不明は空欄
A8: seller_name | B8: text | C8: 売主名の概略 | D8: 詳細売主別株数はseller_breakdownに名称:株数;区切りで記録
A9: seller_type | B9: enum | C9: 売主タイプ | D9: nonlife_insurer/bank/trust_bank/business_company/parent_or_affiliate/financial_institutionsなど
A10: relationship | B10: text | C10: 発行体と売主の関係 | D10: 政策保有・親会社・取引先・退職給付信託など
A11: event_tier | B11: enum | C11: イベント確度/用途 | D11: Tier1_confirmed=確定売却、Tier2_candidate=候補/方針、Tier3_overhang=背景圧力
A12: event_role | B12: enum | C12: legの役割 | D12: announcement/pricing/settlement/trade/buyback_decision/buyback_result/policy_intentなど
... A70: notes | B70: text | C70: 注記・不明値理由 | D70: 明記値以外は空欄とし、理由をここに書く

Sheet Lists
A1: status | B1: event_tier | C1: event_role | D1: sale_route | E1: absorption_route | F1: seller_type | G1: quantity_basis | H1: value_basis | I1: ABM_candidate_flag | J1: confidence_policy_holding | K1: activist_pressure | L1: bool
A2: seeded | B2: Tier1_confirmed | C2: announcement | D2: secondary_offering | E2: public_offering | F2: nonlife_insurer | G2: resolution_max | H2: resolution_max | I2: Yes | J2: A_explicit_policy_holding | K2: TRUE | L2: TRUE
A3: candidate | B3: Tier2_candidate | C3: pricing | D3: toSTNeT_3 | E3: toSTNeT_3_buyback | F3: bank | G3: priced_final | H3: priced_final | I3: No | J3: B_strong_inference | K3: FALSE | L3: FALSE
A4: needs_source_check | B4: Tier3_overhang | C4: settlement | D4: share_forward | E4: issuer_buyback | F4: trust_bank | G4: estimate_close_price | H4: estimate_close_price | I4: Maybe | J4: C_possible_only | K4: unknown
A5: needs_price_data | C5: trade | D5: block_trade | E5: underwriter_inventory | F5: business_company | G5: executed_actual | H5: executed_actual | J5: D_not_policy_holding
A6: complete | C6: buyback_decision | D6: open_market_sale | E6: counterparty_bank_forward | F6: parent_or_affiliate | G6: announced_total | H6: announced_total
A7: exclude | C7: buyback_result | D7: market_sale_undetermined | E7: public_market | F7: financial_institutions
C8: policy_intent | D8: self_tender_offer | E8: none | F8: mixed_financials
C9: other | D9: mixed | E9: unknown | F9: mixed
D10: unknown | F10: unknown

Sheet Baseline_Spec
A1: Step | B1: Model | C1: Formula / Test | D1: Decision Rule
A2: 0 | B2: Sample definition | C2: Main sample = Tier1_confirmed and confidence A/B | D2: Do not mix Tier2/3 into execution-impact regressions
A3: 1 | B3: Size/ADV | C3: impact = α + β log(size / ADV20) | D3: If this explains everything, ABM is unnecessary
A4: 2 | B4: Square-root impact | C4: impact = Y × σ × sqrt(Q/V) | D4: Use as external-impact benchmark
A5: 3 | B5: Route/support FE | C5: impact ~ log(size/ADV) + log(size/free_float) + vol + seller_type + route + buyback_support + OA + industry FE + month FE | D5: Route係数は記述統計。route is endogenously selected; do not read as causal effect.
A6: 3.5 | B6: Route choice / selection function | C6: Estimate P(route | observables). route is endogenously selected, so Step 3 route coefficients are descriptive rather than causal. | D6: ABM validation targets: (a) overlapping size/ADV band where multiple routes coexist, (b) contrast events with vs without buyback support.
A7: 4 | B7: Discount model | C7: discount ~ size/ADV + volatility + route + seller_type + OA + buyback_support | D7: Separate pricing concession from announcement CAR
A8: 5 | B8: Residual clustering | C8: residual ~ low free float × large size × no buyback etc. | D8: ABM only where residuals are non-random and mechanism-like
A9: 6 | B9: ABM candidate | C9: Scenario search around route boundary, buyback absorption, front-running/liquidity withdrawal, low-liquidity tail | D9: No ABM if residuals are just noise

Sheet Source_Log
A1: source_id | B1: source_type | C1: source_url | D1: what_it_supports | E1: archived | F1: notes
A2: S001 | B2: legal/practice memo | C2: https://www.nagashima.com/wp-content/uploads/2024/12/capital_no44.pdf | D2: Policy shareholding sale methods: offering, block, market, off-auction distribution, bilateral sale, issuer buyback/ToSTNeT-3/self-tender. | E2: =FALSE() -> FALSE
A3: S002 | B3: JPX official | C3: https://www.jpx.co.jp/equities/trading/own-company-shares/index.html | D3: Issuer repurchases can use ToSTNeT-2 and ToSTNeT-3 in addition to regular market buying. | E3: =FALSE() -> FALSE
A4: S003 | B4: Company disclosure | C4: https://global.honda/content/dam/site/global-jp/news-new/cq_img/2024/07/c240704/c240704.pdf | D4: Honda secondary offering and buyback authorization details. | E4: =FALSE() -> FALSE
A5: S004 | B5: Company disclosure | C5: https://www.aisin.com/en/news/uploads/2027062701en.pdf | D5: Aisin secondary offering, sellers, OA, and buyback support. | E5: =FALSE() -> FALSE | F5: URL path contains 2027; 一次PDF保存必須。
A6: S005 | B6: Company disclosure | C6: https://www.nse.or.jp/listing/search/files/140120240328562091.pdf | D6: DENSO sale of Toyota Industries shares and share forward agreement designed to limit market impact. | E6: =FALSE() -> FALSE
A7: S006 | B7: Company disclosure | C7: https://www.taxan.co.jp/jp/ir/upload_file/tdnrelease/8154_20250807533725_P01_.pdf | D7: Kaga Electronics ToSTNeT-3 buyback prompted by bank policy holding reduction. | E7: =FALSE() -> FALSE
A8: S007 | B8: Company disclosure | C8: https://www.nintendo.co.jp/ir/pdf/2026/260227.pdf | D8: Nintendo secondary offering and sellers. | E8: =FALSE() -> FALSE
A9: S008 | B9: Company disclosure | C9: https://www.nintendo.co.jp/ir/pdf/2026/260227_2.pdf | D9: Nintendo ToSTNeT-3 buyback authorization. | E9: =FALSE() -> FALSE
A10: S009 | B10: Company disclosure | C10: https://finance-frontend-pc-dist.west.edge.storage-yahoo.jp/disclosure/20260303/20260302574028.pdf | D10: DeNA sale into Nintendo ToSTNeT-3 buyback and reduction of planned offering shares. | E10: =FALSE() -> FALSE | F10: Yahoo CDN直リンク。一次PDF保存必須。
A11: S010 | B11: Reuters | C11: https://www.reuters.com/sustainability/sustainable-finance-reporting/nintendo-plans-around-19-billion-share-sale-by-kyoto-bank-others-sources-say-2026-02-27/ | D11: Reuters estimate of Nintendo share sale value and context of strategic shareholding unwind. | E11: =FALSE() -> FALSE
A12: S011 | B12: Company disclosure | C12: https://www.nintendo.co.jp/ir/pdf/2026/security_q2603.pdf | D12: Nintendo FY2026/3有報: 自己株式11,430,000株の取得・消却実績(G008 L002の裏付け) | E12: False
A13: S012 | B13: Company disclosure | C13: https://www.thepack.co.jp/dcms_media/other/2025.08.29b.pdf | D13: The Pack 売出し・買付支援の一次開示(G006) | E13: False
A14: S013 | B14: Company disclosure | C14: https://www.nishikawa-rbr.co.jp/upfile/20260119_3_news.pdf | D14: Daikyo Nishikawa 売出し一次開示(G007) | E14: False
A15: S014 | B15: Company disclosure | C15: https://www.toyota-industries.com/news/2023/11/29/008606/index.html | D15: DENSO売出しへのToyota Industries参加表明(G001) | E15: False
A16: S015 | B16: Reuters | C16: https://www.reuters.com/business/autos-transportation/toyota-group-companies-offload-some-1-bln-aisin-shares-2024-06-27/ | D16: Aisin売出し規模の報道(G003 secondary) | E16: False | F16: paywall/robotsで自動保存不可の可能性
A17: S016 | B17: Reuters | C17: https://www.reuters.com/business/autos-transportation/japanese-insurers-banks-sell-honda-shares-worth-33-bln-filing-shows-2024-07-04/ | D17: Honda売出し規模の報道(G004 secondary) | E17: False | F17: paywall/robotsで自動保存不可の可能性
A18: S017 | B18: Company disclosure | C18: https://finance-frontend-pc-dist.west.edge.storage-yahoo.jp/disclosure/20260227/20260227571366.pdf | D18: DeNA応募・売出株数減少の開示PDF控え(G008 L002 secondary) | E18: False | F18: Yahoo CDN直リンク。一次PDF保存必須

Sheet README
A1: Policy Holding Sale Event Tape v0.4
A2: 改修日 | B2: 46210
A3: 目的 | B3: 政策保有株式の解消・売却イベントを、売却構造・吸収/支援パッケージ・流動性制約・価格影響に分解して記録するための台帳。
A4: v0.2方針 | B4: データ創作禁止。指示書に明記された値と既存v0.1の値のみ保持し、不明値は空欄＋notesで理由を記録する。Web取得・外部データ追加なし。
A5: イベント単位 | B5: 1行=issuer × route × tranche/leg。親イベントevent_group_idと子イベントevent_leg_idを分離。売主別分割はせずseller_breakdownに「名称:株数;」で記録する。
A6: day0規則 | B6: day 0 = 反応可能な最初の立会。disclosure_timeとafter_closeを使い、引け後開示なら翌営業日をday 0とする。
A7: 分析方針 | B7: まず構造タグ付きイベントTCAを作り、size/ADV・square-root・route/support FE・route choiceで説明できない残差パターンだけをABM候補にする。
A8: 主分析サンプル | B8: Tier1_confirmedかつconfidence A/Bを主分析対象にする。Tier2_candidateは候補、Tier3_overhangは背景変数として扱う。
A9: 注意 | B9: CAR、ADV、free float、時価総額、drift/recovery等は価格データ取得後に入力・計算する。v0.2では価格系列取得を行っていない。
A10: v0.3改修 | B10: 監査修正: シート名Event_Tape化、Dashboard数式復元、basisにannounced_total追加・全行付与、TRUE/FALSE表記統一、候補行に証券コード付与、任天堂L002を有報と突合(S011)、enumデータ検証と先頭列固定を追加
A11: v0.4修復 | B11: v0.2生成時のセル切り詰め(80字+『...』)27件をv0.1原本から復元。Source_LogにS012-S017を追加し、legs上の全URLをSource_Log登録済みに

Sheet Sampling_Frame
A1: Sampling_Frame v0.2 draft
A2: period_start | B2: 2023-01-01
A3: period_end | B3: 2026-06-30
A4: population_candidate_1 | B4: TDnet開示の「株式の売出し」× 政策保有・持ち合い関連キーワード
A5: population_candidate_2 | B5: TDnet開示の「自己株式の取得(ToSTNeT-3含む)」× 政策保有・持ち合い関連キーワード
A6: population_candidate_3 | B6: TDnet開示の「自己株式の公開買付け」× 政策保有・持ち合い関連キーワード
A7: population_candidate_4 | B7: EDINET変更報告書
A8: population_candidate_5 | B8: 有価証券報告書の特定投資株式テーブルの年次差分
A9: exclude_candidate_1 | B9: 新株発行を伴う公募
A10: exclude_candidate_2 | B10: 非公開化TOB
A11: status | B11: ドラフト。母集団定義の確定はユーザーが行う。

Sheet Changelog
A1: change_id | B1: sheet | C1: cell_or_range | D1: change_type | E1: details | F1: reason/instruction
A2: C001 | B2: Event_Tape_v0.1 | C2: Header row A1:BQ1 | D2: schema_add | E2: disclosure_time, after_close, quantity_basis, value_basis, initial_offer_shares, final_offer_shares, OA_exercised_shares, buyback_cancellation, lockup_days, lead_underwriter, seller_breakdown, activist_pressure, drift_ann_to_pricing, recovery_60d を追加 | F2: 変更1
A3: C002 | B3: Event_Tape_v0.1 | C3: G005 / L001 | D3: row_correction | E3: value_basis=resolution_max, quantity_basis=resolution_max, sold_value_JPY=150億円を決議上限として保持。notesに4,920,000株×2,938円=約144.5億円および実績leg追加予定を記載 | F3: 変更4
A4: C003 | B4: Event_Tape_v0.1 | C4: G004 / L001 | D4: row_correction | E4: value_basis=estimate_close_price。notesにReuters推定値である旨を追記 | F4: 変更4
A5: C004 | B5: Event_Tape_v0.1 | C5: G008 / L001 | D5: row_correction | E5: disclosure_time=15:40, after_close=TRUE, seller_breakdownを指定値で入力, initial_offer_shares=32,697,900, buyback_size_shares=14,000,000, buyback_value_JPY=1,000億円, buyback_window=2026-03-03 to 2026-03-04, buyback_cancellation=TRUE, activist_pressure=TRUE | F5: 変更4
A6: C005 | B6: Event_Tape_v0.1 | C6: G008 / L001 route_notes/notes | D6: text_sync | E6: 条件決定期間2026-03-09〜2026-03-12、自己株取得に伴い買取引受・OAの売出株式数が減少し得る旨、DeNA売却背景の旧村上系アクティビスト関与報道を追記 | F6: 変更4
A7: C006 | B7: Event_Tape_v0.1 | C7: G009:G011 | D7: row_add | E7: 信越化学、イビデン、ニチレイをTier2_candidate/status=candidateで追加。数値欄は空欄、notes=要一次資料 | F7: 変更5
A8: C007 | B8: Lists | C8: A1:L10 | D8: sheet_rebuild | E8: 1フィールド=1列、先頭行=フィールド名に再構成。新enumを追加しField_Dictionaryと同期 | F8: 変更2
A9: C008 | B9: Baseline_Spec | C9: Row 6 / Step 3.5 | D9: row_insert | E9: 選択関数 P(route | 観測量) の推定を追加。route係数は記述統計で因果効果ではないこと、ABM検証ターゲットを明記 | F9: 変更3
A10: C009 | B10: Source_Log | C10: Header + S004/S009 | D10: schema_add_and_notes | E10: archived列を追加し全行FALSEで初期化。Aisin URL異常とYahoo CDN直リンクに一次PDF保存必須メモを追加 | F10: 変更4
A11: C010 | B11: Sampling_Frame | C11: New sheet | D11: sheet_add | E11: 2023-01-01〜2026-06-30の母集団定義ドラフトを追加 | F11: 変更6
A12: C011 | B12: README | C12: A1:B9 | D12: doc_sync | E12: v0.2方針、day0規則、サンプル方針、データ未取得方針を同期 | F12: 変更7
... A29: C028 | B29: README/Dashboard | C29: A1 | D29: update | E29: タイトルをv0.4に更新 | F29: v0.4修復
